SuanfaTongguanShouceItcharge/README.md
SuanfaTongguanShouceItcharge/__init__.py
SuanfaTongguanShouceItcharge/__main__.py
SuanfaTongguanShouceItcharge/file.epub
SuanfaTongguanShouceItcharge/index.html
SuanfaTongguanShouceItcharge/css/__init__.py
SuanfaTongguanShouceItcharge/css/annotations.css
SuanfaTongguanShouceItcharge/css/main.css
SuanfaTongguanShouceItcharge/css/normalize.css
SuanfaTongguanShouceItcharge/css/popup.css
SuanfaTongguanShouceItcharge/font/__init__.py
SuanfaTongguanShouceItcharge/font/fontello.eot
SuanfaTongguanShouceItcharge/font/fontello.svg
SuanfaTongguanShouceItcharge/font/fontello.ttf
SuanfaTongguanShouceItcharge/font/fontello.woff
SuanfaTongguanShouceItcharge/img/__init__.py
SuanfaTongguanShouceItcharge/img/annotator-glyph-sprite.png
SuanfaTongguanShouceItcharge/img/annotator-icon-sprite.png
SuanfaTongguanShouceItcharge/img/apple-touch-icon.png
SuanfaTongguanShouceItcharge/img/cancelfullscreen.png
SuanfaTongguanShouceItcharge/img/close.png
SuanfaTongguanShouceItcharge/img/fullscreen.png
SuanfaTongguanShouceItcharge/img/loader.gif
SuanfaTongguanShouceItcharge/img/menu-icon.png
SuanfaTongguanShouceItcharge/img/save.png
SuanfaTongguanShouceItcharge/img/saved.png
SuanfaTongguanShouceItcharge/img/settings-s.png
SuanfaTongguanShouceItcharge/img/settings.png
SuanfaTongguanShouceItcharge/img/star.png
SuanfaTongguanShouceItcharge/js/__init__.py
SuanfaTongguanShouceItcharge/js/epub.js
SuanfaTongguanShouceItcharge/js/epub.min.js
SuanfaTongguanShouceItcharge/js/epub.min.map
SuanfaTongguanShouceItcharge/js/hooks.min.js
SuanfaTongguanShouceItcharge/js/hooks.min.map
SuanfaTongguanShouceItcharge/js/reader.js
SuanfaTongguanShouceItcharge/js/reader.js.map
SuanfaTongguanShouceItcharge/js/reader.min.js
SuanfaTongguanShouceItcharge/js/reader.min.map
SuanfaTongguanShouceItcharge/js/hooks/__init__.py
SuanfaTongguanShouceItcharge/js/hooks/extensions/__init__.py
SuanfaTongguanShouceItcharge/js/hooks/extensions/highlight.js
suanfa_tongguan_shouce_itcharge-2024.3.6.0.dist-info/METADATA
suanfa_tongguan_shouce_itcharge-2024.3.6.0.dist-info/WHEEL
suanfa_tongguan_shouce_itcharge-2024.3.6.0.dist-info/entry_points.txt
suanfa_tongguan_shouce_itcharge-2024.3.6.0.dist-info/top_level.txt
suanfa_tongguan_shouce_itcharge-2024.3.6.0.dist-info/RECORD
